odoo10_addon_shopinvader_payment_manual-10.0.2.0.0-py3.8-nspkg.pth
odoo/addons/shopinvader_payment_manual/README.rst
odoo/addons/shopinvader_payment_manual/__init__.py
odoo/addons/shopinvader_payment_manual/__manifest__.py
odoo/addons/shopinvader_payment_manual/components/__init__.py
odoo/addons/shopinvader_payment_manual/components/payment_transaction_event_listerner.py
odoo/addons/shopinvader_payment_manual/demo/payment_demo.xml
odoo/addons/shopinvader_payment_manual/readme/CONTRIBUTORS.rst
odoo/addons/shopinvader_payment_manual/readme/DESCRIPTION.rst
odoo/addons/shopinvader_payment_manual/services/__init__.py
odoo/addons/shopinvader_payment_manual/services/payment_manual.py
odoo/addons/shopinvader_payment_manual/static/description/index.html
odoo10_addon_shopinvader_payment_manual-10.0.2.0.0.dist-info/METADATA
odoo10_addon_shopinvader_payment_manual-10.0.2.0.0.dist-info/WHEEL
odoo10_addon_shopinvader_payment_manual-10.0.2.0.0.dist-info/namespace_packages.txt
odoo10_addon_shopinvader_payment_manual-10.0.2.0.0.dist-info/top_level.txt
odoo10_addon_shopinvader_payment_manual-10.0.2.0.0.dist-info/RECORD
